{"resourceType":"ValueSet","id":"IMMZ.D.DE19","text":{"status":"generated","div":"<div xmlns=\"http://www.w3.org/1999/xhtml\"><p>This value set includes codes based on the following rules:</p><ul/></div>"},"url":"http://smart.who.int/ig/smart-immunizations/ValueSet/IMMZ.D.DE19","version":"0.1.0","name":"IMMZ_D_DE19","title":"IMMZ.D.DE19 ValueSet for Vaccine type","status":"active","date":"2024-01-19T21:33:08+05:00","publisher":"World Health Organization (WHO)","contact":[{"name":"World Health Organization (WHO)","telecom":[{"system":"url","value":"https://www.who.int"}]}],"description":"ValueSet for Vaccine type for IMMZ.D.DE19","jurisdiction":[{"coding":[{"system":"http://unstats.un.org/unsd/methods/m49/m49.htm","code":"001"}]}]}