{
  "unversionedId": "cql/readme",
  "id": "cql/readme",
  "title": "readme",
  "description": "Introduction",
  "source": "@site/docs/cql/readme.md",
  "sourceDirName": "cql",
  "slug": "/cql/",
  "permalink": "/cql/",
  "draft": false,
  "editUrl": "https://github.com/opensrp/fhircore/tree/main/docs/docs/cql/readme.md",
  "tags": [],
  "version": "current",
  "frontMatter": {},
  "sidebar": "defaultSidebar",
  "previous": {
    "title": "Purpose of this document",
    "permalink": "/covax-demo-app"
  },
  "next": {
    "title": "fhir-workflow-summary",
    "permalink": "/fhir-workflow-summary"
  }
}