{
  "resourceType": "QuestionnaireResponse",
  "questionnaire": "Questionnaire/client-registration-sample",
  "item": [
    {"linkId": "patient-barcode"},
    {
      "linkId": "PR",
      "item": [
        {
          "linkId": "PR-name",
          "item": [
            {
              "linkId": "PR-name-text",
              "answer": [
                {
                  "valueString": "testeight"
                }
              ]
            },
            {
              "linkId": "PR-name-family",
              "answer": [
                {
                  "valueString": "eight"
                }
              ]
            }
          ]
        },
        {
          "linkId": "patient-0-birth-date",
          "answer": [
            {
              "valueDate": "2021-07-02"
            }
          ]
        },
        {
          "linkId": "patient-0-gender",
          "answer": [
            {
              "valueCoding": {
                "code": "female",
                "display": "Female"
              }
            }
          ]
        },
        {
          "linkId": "PR-telecom",
          "item": [
            {
              "linkId": "PR-telecom-system",
              "answer": [
                {
                  "valueString": "phone"
                }
              ]
            },
            {
              "linkId": "PR-telecom-value",
              "answer": [
                {
                  "valueString": "57766"
                }
              ]
            }
          ]
        },
        {
          "linkId": "PR-address",
          "item": [
            {
              "linkId": "PR-address-city",
              "answer": [
                {
                  "valueString": "NAIROBI"
                }
              ]
            },
            {
              "linkId": "PR-address-country",
              "answer": [
                {
                  "valueString": "Kenya"
                }
              ]
            }
          ]
        },
        {
          "linkId": "PR-active",
          "answer": [
            {
              "valueBoolean": true
            }
          ]
        }
      ]
    },
    {
      "linkId": "comorbidities",
      "item": [
        {
          "linkId": "diabetes_mellitus"
        },
        {
          "linkId": "hypertension"
        },
        {
          "linkId": "ihd"
        },
        {
          "linkId": "tb"
        },
        {
          "linkId": "copd"
        },
        {
          "linkId": "chronic_kidney_disease"
        },
        {
          "linkId": "cancer"
        },
        {
          "linkId": "others"
        },
        {
          "linkId": "other_comorbidities"
        }
      ]
    },
    {
      "linkId": "risk_assessment",
      "answer": [
        {
          "valueCoding": {
            "system": "https://www.snomed.org",
            "code": "870577009",
            "display": "High Risk for COVID-19"
          }
        }
      ]
    }
  ]
}