{
  "resourceType": "MedicationRequest",
  "status": "active",
  "intent": "proposal",
  "subject": {
    "reference": "Patient/TEST_PATIENT"
  },
  "encounter": {
    "reference": "Encounter/TEST_ENCOUNTER"
  },
  "authoredOn": "#NOW",
  "category": [
    {
      "coding": [
        {
          "system": "http://snomed.info/sct",
          "code": "86859003",
          "display": "Glucose-6-phosphate dehydrogenase deficiency anaemia"
        }
      ]
    }
  ],
  "reasonCode": [
    {
      "coding": [
        {
          "system": "http://snomed.info/sct",
          "code": "86859003",
          "display": "Glucose-6-phosphate dehydrogenase deficiency anaemia"
        }
      ]
    }
  ],
  "medicationCodeableConcept": {
    "coding": [
      {
        "system": "http://snomed.info/sct",
        "code": "429663004",
        "display": "Primaquine (substance)"
      }
    ]
  },
  "dosageInstruction": [
    {
      "timing": {
        "repeat": {
          "frequency": 1,
          "period": 8.0,
          "periodUnit": "wk"
        }
      },
      "route": {"coding":[{"system":"http://snomed.info/sct","code":"26643006","display":"Oral use"}]},
      "doseAndRate": [
        {
          "type": {
            "coding": [
              {
                "system": "http://terminology.hl7.org/CodeSystem/dose-rate-type",
                "code": "ordered",
                "display": "Ordered"
              }
            ]
          },
          "doseQuantity": {
            "value": 0.75,
            "unit": "mg/kg",
            "system":"http://unitsofmeasure.org"
          }
        }
      ]
    }
  ]
}